devpi-ldap.py
devpi_ldap/__init__.py
devpi_ldap/main.py
devpi_ldap-2.1.1.dist-info/METADATA
devpi_ldap-2.1.1.dist-info/WHEEL
devpi_ldap-2.1.1.dist-info/entry_points.txt
devpi_ldap-2.1.1.dist-info/top_level.txt
devpi_ldap-2.1.1.dist-info/RECORD
