Metadata-Version: 2.1
Name: devpi-ldap
Version: 2.1.1
Summary: devpi-ldap: LDAP authentication for devpi-server
Home-page: https://github.com/devpi/devpi-ldap
Maintainer: Florian Schulze
Maintainer-email: mail@pyfidelity.com
License: MIT
Platform: UNKNOWN
Classifier: Environment :: Web Environment
Classifier: Intended Audience :: Developers
Classifier: Intended Audience :: System Administrators
Classifier: License :: OSI Approved :: MIT License
Classifier: Programming Language :: Python
Classifier: Programming Language :: Python :: 3
Classifier: Programming Language :: Python :: 3.6
Classifier: Programming Language :: Python :: 3.7
Classifier: Programming Language :: Python :: 3.8
Classifier: Programming Language :: Python :: 3.9
Classifier: Programming Language :: Python :: 3.10
Classifier: Programming Language :: Python :: 3.11
Requires-Python: >=3.6
Requires-Dist: PyYAML
Requires-Dist: devpi-server >=5
Requires-Dist: ldap3 >=0.9.9.3
